MANIFEST.in
README.rst
README.txt
requirements.txt
setup.cfg
setup.py
djmicrosip_remgencargos/__init__.py
djmicrosip_remgencargos/__init__.pyc
djmicrosip_remgencargos/config.pyc
djmicrosip_remgencargos/forms.pyc
djmicrosip_remgencargos/menu.pyc
djmicrosip_remgencargos/models.pyc
djmicrosip_remgencargos/urls.pyc
djmicrosip_remgencargos/views.pyc
djmicrosip_remgencargos.egg-info/PKG-INFO
djmicrosip_remgencargos.egg-info/SOURCES.txt
djmicrosip_remgencargos.egg-info/dependency_links.txt
djmicrosip_remgencargos.egg-info/requires.txt
djmicrosip_remgencargos.egg-info/top_level.txt
djmicrosip_remgencargos/static/css/images/ui-icons_454545_256x240.png
djmicrosip_remgencargos/static/js/ventas.documentos.remisiones_crear_cargos.js
djmicrosip_remgencargos/templates/djmicrosip_remgencargos/base.html
djmicrosip_remgencargos/templates/ventas/documentos/djmicrosip_remgencargos/remisiones.html